margay/__init__.py
margay/sdk/__init__.py
margay/sdk/auth/__init__.py
margay/sdk/client/__init__.py
margay/sdk/config/__init__.py
margay/sdk/logger/__init__.py
margay/sdk/protocol/__init__.py
margay/sdk/publisher/__init__.py
margay/sdk/subscriber/__init__.py
margay-0.2.0.dist-info/LICENSE
margay-0.2.0.dist-info/METADATA
margay-0.2.0.dist-info/WHEEL
margay-0.2.0.dist-info/top_level.txt
margay-0.2.0.dist-info/RECORD
