Metadata-Version: 2.1
Name: margay
Version: 0.2.0
Summary: SDK for Margay Gateway - provide tooling and examples of usage.
Home-page: https://github.com/moaddib666/wss-api-gateway.sdk.python
Author: Max Nikitenko
Author-email: moaddib666@gmail.com
Keywords: api,geteway,websocket,tools,margay
Platform: any
Classifier: Intended Audience :: Developers
Classifier: License :: OSI Approved :: Apache Software License
Classifier: Programming Language :: Python
Classifier: Programming Language :: Python :: 3
Classifier: Programming Language :: Python :: 3.8
Classifier: Programming Language :: Python :: 3.9
Classifier: Programming Language :: Python :: 3.10
Requires-Python: >=3.8
License-File: LICENSE
Requires-Dist: websocket-client
Requires-Dist: kombu
Requires-Dist: pydantic
Requires-Dist: pyjwt
Provides-Extra: test
